<?xml version="1.0" encoding="utf-8"?>
	<annotation>
		<folder>images</folder>
		<filename>060828381f30e9241b88c53b40086e061d95f788.jpg</filename>
		<path>../train/train/060828381f30e9241b88c53b40086e061d95f788.jpg</path>
		<source>
			<database>Unknown</database>
		</source>
		<size>
			<width>960</width>
			<height>1280</height>
			<depth>3</depth>
		</size>
		<segmented>0</segmented>
		<object>
			<name>store_tag</name>
			<pose>Unspecified</pose>
			<truncated>0</truncated>
			<difficult>0</difficult>
			<bndbox>
				<xmin>682</xmin>
				<ymin>350</ymin>
				<xmax>856</xmax>
				<ymax>454</ymax>
			</bndbox>
		</object>
	</annotation>
