<?xml version="1.0" encoding="utf-8"?>
	<annotation>
		<folder>images</folder>
		<filename>242dd42a2834349b84189f42c0ea15ce37d3bedf.jpg</filename>
		<path>../train/train/242dd42a2834349b84189f42c0ea15ce37d3bedf.jpg</path>
		<source>
			<database>Unknown</database>
		</source>
		<size>
			<width>1600</width>
			<height>1200</height>
			<depth>3</depth>
		</size>
		<segmented>0</segmented>
		<object>
			<name>store_tag</name>
			<pose>Unspecified</pose>
			<truncated>0</truncated>
			<difficult>0</difficult>
			<bndbox>
				<xmin>649</xmin>
				<ymin>89</ymin>
				<xmax>977</xmax>
				<ymax>309</ymax>
			</bndbox>
		</object>
	</annotation>
