<?xml version="1.0" encoding="utf-8"?>
	<annotation>
		<folder>images</folder>
		<filename>32fa828ba61ea8d3ba5521b19c0a304e251f580b.jpg</filename>
		<path>../train/train/32fa828ba61ea8d3ba5521b19c0a304e251f580b.jpg</path>
		<source>
			<database>Unknown</database>
		</source>
		<size>
			<width>960</width>
			<height>1280</height>
			<depth>3</depth>
		</size>
		<segmented>0</segmented>
		<object>
			<name>store_tag</name>
			<pose>Unspecified</pose>
			<truncated>0</truncated>
			<difficult>0</difficult>
			<bndbox>
				<xmin>221</xmin>
				<ymin>448</ymin>
				<xmax>483</xmax>
				<ymax>544</ymax>
			</bndbox>
		</object>
	</annotation>
