<?xml version="1.0" encoding="utf-8"?>
	<annotation>
		<folder>images</folder>
		<filename>359b033b5bb5c9eadb784bfbd939b6003af3b31b.jpg</filename>
		<path>../train/train/359b033b5bb5c9eadb784bfbd939b6003af3b31b.jpg</path>
		<source>
			<database>Unknown</database>
		</source>
		<size>
			<width>960</width>
			<height>1280</height>
			<depth>3</depth>
		</size>
		<segmented>0</segmented>
		<object>
			<name>store_tag</name>
			<pose>Unspecified</pose>
			<truncated>0</truncated>
			<difficult>0</difficult>
			<bndbox>
				<xmin>376</xmin>
				<ymin>125</ymin>
				<xmax>788</xmax>
				<ymax>475</ymax>
			</bndbox>
		</object>
	</annotation>
