<?xml version="1.0" encoding="utf-8"?>
	<annotation>
		<folder>images</folder>
		<filename>35a85edf8db1cb1335bc11e7d654564e93584b68.jpg</filename>
		<path>../train/train/35a85edf8db1cb1335bc11e7d654564e93584b68.jpg</path>
		<source>
			<database>Unknown</database>
		</source>
		<size>
			<width>960</width>
			<height>1280</height>
			<depth>3</depth>
		</size>
		<segmented>0</segmented>
		<object>
			<name>store_tag</name>
			<pose>Unspecified</pose>
			<truncated>0</truncated>
			<difficult>0</difficult>
			<bndbox>
				<xmin>317</xmin>
				<ymin>111</ymin>
				<xmax>627</xmax>
				<ymax>254</ymax>
			</bndbox>
		</object>
	</annotation>
