<?xml version="1.0" encoding="utf-8"?>
	<annotation>
		<folder>images</folder>
		<filename>5366d0160924ab18e4a7b44739fae6cd7b890b08.jpg</filename>
		<path>../train/train/5366d0160924ab18e4a7b44739fae6cd7b890b08.jpg</path>
		<source>
			<database>Unknown</database>
		</source>
		<size>
			<width>768</width>
			<height>1024</height>
			<depth>3</depth>
		</size>
		<segmented>0</segmented>
		<object>
			<name>store_tag</name>
			<pose>Unspecified</pose>
			<truncated>0</truncated>
			<difficult>0</difficult>
			<bndbox>
				<xmin>272</xmin>
				<ymin>357</ymin>
				<xmax>496</xmax>
				<ymax>428</ymax>
			</bndbox>
		</object>
	</annotation>
