<?xml version="1.0" encoding="utf-8"?>
	<annotation>
		<folder>images</folder>
		<filename>80cb39dbb6fd52667195260ea718972bd4073669.jpg</filename>
		<path>../train/train/80cb39dbb6fd52667195260ea718972bd4073669.jpg</path>
		<source>
			<database>Unknown</database>
		</source>
		<size>
			<width>960</width>
			<height>1280</height>
			<depth>3</depth>
		</size>
		<segmented>0</segmented>
		<object>
			<name>store_tag</name>
			<pose>Unspecified</pose>
			<truncated>0</truncated>
			<difficult>0</difficult>
			<bndbox>
				<xmin>538</xmin>
				<ymin>236</ymin>
				<xmax>731</xmax>
				<ymax>357</ymax>
			</bndbox>
		</object>
	</annotation>
