<?xml version="1.0" encoding="utf-8"?>
	<annotation>
		<folder>images</folder>
		<filename>838ba61ea8d3fd1fd0238ffb3a4e251f94ca5fcc.jpg</filename>
		<path>../train/train/838ba61ea8d3fd1fd0238ffb3a4e251f94ca5fcc.jpg</path>
		<source>
			<database>Unknown</database>
		</source>
		<size>
			<width>960</width>
			<height>1280</height>
			<depth>3</depth>
		</size>
		<segmented>0</segmented>
		<object>
			<name>store_tag</name>
			<pose>Unspecified</pose>
			<truncated>0</truncated>
			<difficult>0</difficult>
			<bndbox>
				<xmin>541</xmin>
				<ymin>228</ymin>
				<xmax>856</xmax>
				<ymax>481</ymax>
			</bndbox>
		</object>
	</annotation>
