<?xml version="1.0" encoding="utf-8"?>
	<annotation>
		<folder>images</folder>
		<filename>8b82b9014a90f60315353d993212b31bb151ed63.jpg</filename>
		<path>../train/train/8b82b9014a90f60315353d993212b31bb151ed63.jpg</path>
		<source>
			<database>Unknown</database>
		</source>
		<size>
			<width>960</width>
			<height>1280</height>
			<depth>3</depth>
		</size>
		<segmented>0</segmented>
		<object>
			<name>store_tag</name>
			<pose>Unspecified</pose>
			<truncated>0</truncated>
			<difficult>0</difficult>
			<bndbox>
				<xmin>421</xmin>
				<ymin>433</ymin>
				<xmax>726</xmax>
				<ymax>586</ymax>
			</bndbox>
		</object>
	</annotation>
