<?xml version="1.0" encoding="utf-8"?>
	<annotation>
		<folder>images</folder>
		<filename>962bd40735fae6cd9605746803b30f2442a70f02.jpg</filename>
		<path>../train/train/962bd40735fae6cd9605746803b30f2442a70f02.jpg</path>
		<source>
			<database>Unknown</database>
		</source>
		<size>
			<width>768</width>
			<height>1024</height>
			<depth>3</depth>
		</size>
		<segmented>0</segmented>
		<object>
			<name>store_tag</name>
			<pose>Unspecified</pose>
			<truncated>0</truncated>
			<difficult>0</difficult>
			<bndbox>
				<xmin>281</xmin>
				<ymin>289</ymin>
				<xmax>492</xmax>
				<ymax>382</ymax>
			</bndbox>
		</object>
	</annotation>
