<?xml version="1.0" encoding="utf-8"?>
	<annotation>
		<folder>images</folder>
		<filename>adaf2edda3cc7cd92a09c81e3001213fb90e91d5.jpg</filename>
		<path>../train/train/adaf2edda3cc7cd92a09c81e3001213fb90e91d5.jpg</path>
		<source>
			<database>Unknown</database>
		</source>
		<size>
			<width>960</width>
			<height>1280</height>
			<depth>3</depth>
		</size>
		<segmented>0</segmented>
		<object>
			<name>store_tag</name>
			<pose>Unspecified</pose>
			<truncated>0</truncated>
			<difficult>0</difficult>
			<bndbox>
				<xmin>90</xmin>
				<ymin>106</ymin>
				<xmax>880</xmax>
				<ymax>467</ymax>
			</bndbox>
		</object>
	</annotation>
