<?xml version="1.0" encoding="utf-8"?>
	<annotation>
		<folder>images</folder>
		<filename>aec379310a55b31954d9861c48a98226cffc17b2.jpg</filename>
		<path>../train/train/aec379310a55b31954d9861c48a98226cffc17b2.jpg</path>
		<source>
			<database>Unknown</database>
		</source>
		<size>
			<width>960</width>
			<height>1280</height>
			<depth>3</depth>
		</size>
		<segmented>0</segmented>
		<object>
			<name>store_tag</name>
			<pose>Unspecified</pose>
			<truncated>0</truncated>
			<difficult>0</difficult>
			<bndbox>
				<xmin>217</xmin>
				<ymin>144</ymin>
				<xmax>496</xmax>
				<ymax>300</ymax>
			</bndbox>
		</object>
	</annotation>
