<?xml version="1.0" encoding="utf-8"?>
	<annotation>
		<folder>images</folder>
		<filename>b8014a90f603738dff239fa7b91bb051f919ecce.jpg</filename>
		<path>../train/train/b8014a90f603738dff239fa7b91bb051f919ecce.jpg</path>
		<source>
			<database>Unknown</database>
		</source>
		<size>
			<width>960</width>
			<height>1280</height>
			<depth>3</depth>
		</size>
		<segmented>0</segmented>
		<object>
			<name>store_tag</name>
			<pose>Unspecified</pose>
			<truncated>0</truncated>
			<difficult>0</difficult>
			<bndbox>
				<xmin>285</xmin>
				<ymin>351</ymin>
				<xmax>829</xmax>
				<ymax>483</ymax>
			</bndbox>
		</object>
	</annotation>
