<?xml version="1.0" encoding="utf-8"?>
	<annotation>
		<folder>images</folder>
		<filename>bd315c6034a85edfbe00ab1043540923dd547570.jpg</filename>
		<path>../train/train/bd315c6034a85edfbe00ab1043540923dd547570.jpg</path>
		<source>
			<database>Unknown</database>
		</source>
		<size>
			<width>960</width>
			<height>1280</height>
			<depth>3</depth>
		</size>
		<segmented>0</segmented>
		<object>
			<name>store_tag</name>
			<pose>Unspecified</pose>
			<truncated>0</truncated>
			<difficult>0</difficult>
			<bndbox>
				<xmin>134</xmin>
				<ymin>86</ymin>
				<xmax>578</xmax>
				<ymax>376</ymax>
			</bndbox>
		</object>
	</annotation>
