<?xml version="1.0" encoding="utf-8"?>
	<annotation>
		<folder>images</folder>
		<filename>bd3eb13533fa828b423368f3f11f4134970a5a8a.jpg</filename>
		<path>../train/train/bd3eb13533fa828b423368f3f11f4134970a5a8a.jpg</path>
		<source>
			<database>Unknown</database>
		</source>
		<size>
			<width>1200</width>
			<height>1600</height>
			<depth>3</depth>
		</size>
		<segmented>0</segmented>
		<object>
			<name>store_tag</name>
			<pose>Unspecified</pose>
			<truncated>0</truncated>
			<difficult>0</difficult>
			<bndbox>
				<xmin>423</xmin>
				<ymin>253</ymin>
				<xmax>997</xmax>
				<ymax>601</ymax>
			</bndbox>
		</object>
	</annotation>
