<?xml version="1.0" encoding="utf-8"?>
	<annotation>
		<folder>images</folder>
		<filename>cefc1e178a82b901fd34b5ff7a8da9773812ef65.jpg</filename>
		<path>../train/train/cefc1e178a82b901fd34b5ff7a8da9773812ef65.jpg</path>
		<source>
			<database>Unknown</database>
		</source>
		<size>
			<width>960</width>
			<height>1280</height>
			<depth>3</depth>
		</size>
		<segmented>0</segmented>
		<object>
			<name>store_tag</name>
			<pose>Unspecified</pose>
			<truncated>0</truncated>
			<difficult>0</difficult>
			<bndbox>
				<xmin>248</xmin>
				<ymin>72</ymin>
				<xmax>649</xmax>
				<ymax>341</ymax>
			</bndbox>
		</object>
	</annotation>
