<?xml version="1.0" encoding="utf-8"?>
	<annotation>
		<folder>images</folder>
		<filename>e824b899a9014c084eb4efbf067b02087bf4f419.jpg</filename>
		<path>../train/train/e824b899a9014c084eb4efbf067b02087bf4f419.jpg</path>
		<source>
			<database>Unknown</database>
		</source>
		<size>
			<width>768</width>
			<height>1024</height>
			<depth>3</depth>
		</size>
		<segmented>0</segmented>
		<object>
			<name>store_tag</name>
			<pose>Unspecified</pose>
			<truncated>0</truncated>
			<difficult>0</difficult>
			<bndbox>
				<xmin>345</xmin>
				<ymin>372</ymin>
				<xmax>418</xmax>
				<ymax>425</ymax>
			</bndbox>
		</object>
	</annotation>
